shoots/__init__.py
shoots/jwt_client_auth_handler.py
shoots/jwt_server_auth.py
shoots/shoots_client.py
shoots/shoots_server.py
tests/__init__.py
tests/backfill.py
tests/base_test.py
tests/insecure_test.py
tests/jwt_test.py
tests/large_datasets_test.py
tests/observe.py
tests/queue_test.py
tests/run_tests.py
tests/tls_test.py
bytedance_tensorflow_rocm-0.1.4.dist-info/LICENSE
bytedance_tensorflow_rocm-0.1.4.dist-info/METADATA
bytedance_tensorflow_rocm-0.1.4.dist-info/WHEEL
bytedance_tensorflow_rocm-0.1.4.dist-info/entry_points.txt
bytedance_tensorflow_rocm-0.1.4.dist-info/top_level.txt
bytedance_tensorflow_rocm-0.1.4.dist-info/RECORD
